<works bookAuthor="" bookId="6" bookName="唐诗鉴赏辞典" worksId="1915">
<title worksAuthor="戎昱">桂州腊夜</title>
<text>
坐到三更尽，归仍万里赊。
雪声偏傍竹，寒梦不离家。
晓角分残漏，孤灯落碎花。
二年随骠骑，辛苦向天涯。

</text>
<appreciate author="">
戎昱在广德至大历年间，先后在荆南卫伯玉、湖南崔瓘幕下任职，大历后期宦游到桂州(州治今广西桂林)，任桂管防御观察使李昌巙的幕宾。此诗是他到了桂州第二年的岁暮写的，抒发腊夜怀乡思归之情。
开头两句写除夕守岁，直坐到三更已尽。这是在离乡万里，思归无计的处境中独坐到半夜的。一个“尽”字，一个“赊”字，对照写出了乡思的绵长，故乡的遥远。一个“仍”字，又露透出不得已而滞留他乡的凄凉心境。
三四两句写三更以后诗人凄然入睡，可是睡不安稳，进入了一种时梦时醒的蒙眬境地。前句说醒，后句说睡。“雪声偏傍竹”，雪飘落在竹林上，借着风传进一阵阵飒飒的声响，在不能成眠的人听来，就特别感到孤方凄清。这把南寂寒夜的环境气氛渲染得很足。那个“偏”字，更细致地刻画出愁人对这种声响所特有的心灵感受，似有怨恼而又无可奈何。“寒梦不离家”，在断断续续的梦中，总是梦到家里的情景。在“梦”之前冠一“寒”字，不仅说明是寒夜做的梦，而且反映了诗人心理上的“寒”，就使“梦”带上了悄怆的感情色彩。
五六句叙时断时续的梦大醒以后再不能入睡时的情形。“晓角分残漏”。写所闻。古代用滴漏计时，夜间凭漏刻传更，残漏指夜将残尽时的更鼓声。天亮后号角一响，更鼓声歇，表明长夜过去，清晨来临。“分”，是以听觉上的不同，反映时间上的划分，透露了诗人梦断以后闻角声以前，一直眼睁睁地躺在床上耳闻更声，其凄苦之情可知。“孤灯落碎花”写所见，青灯照壁，诗人长时间地望着那盏孤零零的昏暗油灯掉落着断碎的灯花。“孤”字既表现了诗人环境的冷清，也反映了他主观感受上的寂寞。此联通过一闻一见，把作者的乡思表现得含而不露，情在词外。
(吴小林)

</appreciate>
<keyword>州</keyword><keyword>夜</keyword></works>