<works bookAuthor="" bookId="6" bookName="唐诗鉴赏辞典" worksId="1936">
<title worksAuthor="刘长卿">余干旅舍</title>
<text>
摇落暮天迥，青枫霜叶稀。
孤城向水闭，独鸟背人飞。
渡口月初上，邻家渔未归。
乡心正欲绝，何处捣寒衣？

</text>
<appreciate author="">
本诗是刘长卿寄寓在余干(今属江西)旅舍时，写下的风调凄清的思乡之作。
刘长卿喜欢用“摇落”这个词入诗，它使人自然联想起《楚辞?九辩》中的名句：“悲哉秋之为气也，萧瑟兮草木摇落而变衰”，而在眼前浮现出一幅西风落叶图。
这首诗开头写诗人独自在旅舍门外伫立凝望，由于草木摇落，整个世界显得清旷疏朗起来。淡淡的暮色，铺展得那样悠远，一直漫到了天的尽头。原先那一片茂密的青枫，也早过了“霜叶红于二月花”的佳境，眼前连霜叶都变得稀稀落落，眼看就要凋尽了。这一番秋景描写，既暗示了时光节令的流逝推移，又烘托了诗人情怀的凄清冷寂，隐隐透露出一种郁郁的离情乡思。
望着望着，暮色渐深，余干城门也关闭起来了，这冷落的氛围给诗人带来孤苦的感受：秋空寥廓，草木萧瑟，白水呜咽，城门紧闭，连城也显得孤孤单单的。独鸟背人远去，那况味是难堪的。“独鸟背人飞”，似乎也暗喻诗人的孤苦背时，含蕴着宦途坎坷的深沉感慨。
随着时间推移，夜幕降临，一规新月正在那水边的渡口冉冉上升。往日此时，邻家的渔船早已傍岸，可今晚，渡口却是这样寂静，连渔船的影子都没有，渔家怎么还不归来呢？诗人的体察是细微的，由渡口的新月，念及邻家的渔船未归，从渔家未归，当然又会触动自己的离思，家人此刻也当在登楼望远，“天际识归舟”吧？
诗写到这里，乡情旅思已经写足。尾联翻出新境，把诗情又推进一层。诗人凭眺已久，乡情愁思正不断侵袭着他的心灵，不知从哪里又传来一阵捣衣的砧声。是谁家少妇正在闺中为远方的亲人赶制寒衣？在阒寂的夜空中，那砧声显得分外清亮，一声声简直把诗人的心都快捣碎了。这一画外音的巧妙运用，更加真切感人地抒写出诗人满怀的悲愁痛苦。家中亲人此时又在做什么呢？兴念及此，能不回肠荡气，五脏欲摧？诗虽然结束了，那凄清的乡思，那缠绵的苦情，却还象无处不在的月光，拂之下去，剪之不断，久久萦绕，困搓扰着诗人不平静的心，真可说是言有尽而意无穷。
(徐竹心)

</appreciate>
<keyword>旅</keyword></works>