<works bookAuthor="" bookId="6" bookName="唐诗鉴赏辞典" worksId="2119">
<title worksAuthor="韦应物">初发扬子寄元大校书</title>
<text>
凄凄去亲爱，泛泛入烟雾。
归棹洛阳人，残钟广陵树。
今朝此为别，何处还相遇？
世事波上舟，沿洄安得住！

</text>
<appreciate author="">
这首诗写于韦应物离开广陵(今江苏扬州)回洛阳去的途中。元大(大是排行，其人名字已不可考)是他在广陵的朋友，诗中用“亲爱”相称，可见彼此感情颇深。所以诗人在还能望见广陵城外的树和还能听到寺庙钟声的时候，就想起要写诗寄给元大了。
这首诗是以“归棹洛阳人，残钟广陵树”十个字著名的。为什么这十个字能脍炙人口呢？
诗人和元大分手，心情很悲伤。可是船终于开行了。船儿飘荡在烟雾之中，他还不住回头看着广陵城，那城外的树林变得愈来愈模糊难辨，这时候，忽又传来在广陵时听惯了的寺庙钟声，一种不得不离开而又舍不得同朋友分离的矛盾心情，和响钟的袅袅余音、城外迷蒙中的树色交织在一起了。诗人没有说动情的话，而是通过形象来抒情，并且让形象的魅力感染了读者。“残钟广陵树”这五个字，感情色彩是异常强烈的。
然而，假如我们追问一下：“残钟广陵树“五个字，只不过写了远树和钟声，何以便产生这样的感情效果？因为光看这五个字，不能肯定说表示了什么感情，更不用说是愁情了。而它之能够表现出这种特殊的感情，是和上文一路逼拢过来的诗情分不开的。这便是客观的形象受到感情的色彩照射后产生的特殊效果。
试看开头的“凄凄去亲爱，泛泛入烟雾”，就已透出惜别好友之情。接以“归棹洛阳人”(自己不能不走)，再跌出“残钟广陵树”，这五个字便如晚霞受到夕阳的照射，特别染上一层离情别绪的特殊颜色。这就比许多难舍难分的径情直述，还要耐人体味了。
下面，“今朝此为别”四句，一方面是申述朋友重逢的不易；一方面又是自开自解：世事本来就不能由个人作主，正如波浪中的船，要么就给水带走，要么就在风里打旋，是不由你停下来的。这样，既是开解自己，又是安慰朋友。
(刘逸生)

</appreciate>
<keyword>寄</keyword></works>