<works bookAuthor="" bookId="6" bookName="唐诗鉴赏辞典" worksId="2363">
<title worksAuthor="刘皂">旅次朔方</title>
<text>
客舍并州已十霜，归心日夜忆咸阳。
无端更渡桑乾水，却望并州是故乡。

</text>
<appreciate author="">
在许多诗集中，这首诗都归在贾岛名下，其实是错误的。因为贾岛是范阳(今北京市大兴县)人，不是咸阳(今陕西省咸阳市)人，而在贾岛自己的作品以及有关这位诗人生平的文献中，从无他在并州作客十年的记载。又此诗风格沉郁，与贾诗之以清奇僻苦见长者很不相类。《元和御览诗集》认为它出于贞元间诗人刘皂之手。虽然今天对刘皂的生平也不详知，但元和与贞元时代相接，《元和御览诗集》的记载应当是可信的。因此，我们定其为刘作。
此诗题目，或作《渡桑乾》，或作《旅次朔方》。前者无须说明，后者却要解释一下。朔方始见《尚书?尧典》，即北方。但同时又是一个地名，始见《诗经?小雅?出车》。西汉置朔方刺史部(当今内蒙古自治区及陕西省的一部分，所辖有朔方郡)，与并州刺史部(当今山西省)相邻。桑乾河并不流经朔方刺史部或朔方郡，所以和朔方之地无关。并州在唐时是河东道，桑乾河由东北而西南，流经河东道北部，横贯蔚州北部，云、朔等州南部。这些州，当今雁北地区。由此可见，诗题朔方，乃系泛称，用法和曹植《送应氏》“我友之朔方，亲昵并集送”一样。而刘皂客舍十年之并州，具体地说，乃是并州北部桑乾河以北之地。
(沈祖棻程千帆)

</appreciate>
<keyword>旅</keyword></works>