<works bookAuthor="" bookId="6" bookName="唐诗鉴赏辞典" worksId="2537">
<title worksAuthor="于濆">古宴曲</title>
<text>
雉扇合蓬莱，朝车回紫陌。
重门集嘶马，言宴金张宅。
燕娥奉卮酒，低鬟若无力。
十户手胼胝，凤凰钗一只。
高楼齐下视，日照罗衣色。
笑指负薪人，不信生中国。

</text>
<appreciate author="">
这是一首以写宴会为中心的诗，主旨在于讽刺过着奢华生活的达官贵人们对于民生疾苦的惊人的无知。题目中用了一个“古”字，诗作中用了汉朝著名的官僚世族金、张两个大姓，都是以汉寓唐、借古事以写时事的意思。
开头四句写朝罢赴宴。首句中的“雉扇”，即“雉尾扇”，用野鸡毛制成的宫扇，是帝王仪仗的一种。头两句写退朝，从皇帝与臣子两面写出：蓬莱宫中的仪仗已经收起来了，大路上滚动着朝罢归来的车子。三、四句写朝罢无事，便聚集到一起宴饮取乐。在开头这四句中，不直接写人，但有车马，有重门，又上朝，又宴饮，可以想见其中活动的人物既富且贵的气派。
中间四句写宴饮席上的盛况。“燕娥”，燕地的美女，宴席上有侍女把酒侍候。“低鬟”是低头之意。“低鬟若无力”是极写捧酒美女娇羞婀娜的仪态。由“低鬟”，又写到鬟髻上凤凰花饰的金钗。“胼胝”指手掌上磨成老茧。诗人仿佛指着金钗在说：别看它小，那是十户人家辛勤劳动的血汗结晶啊！这四句用笔十分干净：写宴席，只写了送酒的美女；写美女，除了表明她的身份，让她捧上酒器以外，只写了她低鬟时所见的那一支金钗。由金钗足以想见美女之高雅，由捧酒美女之高雅也就更可想见座客之高贵与宴席之丰盛了。这种“烘云托月”的侧面描写，是运用得很成功的。
末四句写宴罢后的消遣。酒醉饭饱，不免要游目骋怀一番。一个“齐”字，表明凭栏下视的是许多人。阳光下，他们的罗绮华服显得格外耀眼。当樵夫从高楼附近经过时，贵官们带笑指点着议论起来，不相信国中竟然还有这样的穷苦百姓。最后这四句将全诗推到了一个新的思想境界，诗人在展示了这些上层官僚养尊处优的生活之后，又进而揭示了他们精神世界的极端空虚与愚昧无知。在艺术上，这末四句也是全诗最有光彩的地方。诗人让人物现身说法，登台表演：让“手胼胝”的樵夫出现在画面上，让满座高朋一齐涌向楼头。诗人唯恐艺术效果不佳，还布置了聚光灯──“日照”，让这一帮达官贵人们在光天化日下亮相、表演。在“日照”下，读者不仅见到了这些人耀眼的服饰，而且还从他们的言谈举止中看透了他们卑劣的灵魂。
(陈志明)

</appreciate>
<keyword>古</keyword><keyword>曲</keyword></works>